<item>
    <title>Collaboration with P.O.S</title>
    <link>http://www.crimethinc.com/blog/2012/10/22/collaboration-with-p-o-s/</link>
    <pubDate>Mon, 22 Oct 2012 18:37:24 +0000</pubDate>
    <dc_creator><![CDATA[b. traven]]></dc_creator>
    <guid isPermaLink="false">http://www.crimethinc.com/blog/?p=3529</guid>
    <description/>
    <content_encoded><![CDATA[<p>We're excited to announce our collaboration with Minneapolis rapper <a href="http://rhymesayers.com/pos/">P.O.S</a> in distributing over 600 copies of our <a href="http://www.crimethinc.com/work"><em>Work</em> book</a> and several times that many <a href="http://www.crimethinc.com/tools/posters.html">"Capitalism Is a Pyramid Scheme" posters</a> in preorders for his excellent new album, <a href="http://rhymesayers.com/releases/166">"We Don't Even Live Here,"</a> on Rhymesayers Entertainment.</p>

<p>P.O.S approached us some time ago about including our material in this release, his fourth solo album, which deals with some of the same subjects. We were flattered to receive this invitation from someone whose music we appreciate so much. His razor-sharp wit opens windows on startling vulnerability; his insouciance comes off a thousand times realer than garden-variety hip hop posturing. And we think it's high time that someone in his position reached out to combine art with radical points of departure: music should offer emergency escape hatches out of this world, not just temporary vacations from it.</p>

<p>We're interested in future collaborations with other musicians, artists, and anyone else who wants to shake things up. But P.O.S got there first, and he deserves credit for that.</p>

<p>A big thanks to him and his team for making this happen. We're looking forward to making contact with everyone who learns about our projects via his album.</p>

<!--more Video for "Fuck Your Stuff" after the jump.-->

<iframe width="485" height="273" src="http://www.youtube-nocookie.com/embed/_jj8ltpYJtQ?rel=0" frameborder="0" allowfullscreen></iframe>

<p><em>[Banner photos courtesy of awesomely enthusiastic folks on Twitter.]</em></p>
]]></content_encoded>
    <excerpt:encoded><![CDATA[]]></excerpt:encoded>
    <wp_post_id>3529</wp_post_id>
    <wp_post_date><![CDATA[2012-10-22 18:37:24]]></wp_post_date>
    <wp_post_date_gmt><![CDATA[2012-10-22 18:37:24]]></wp_post_date_gmt>
    <wp_comment_status><![CDATA[open]]></wp_comment_status>
    <wp_ping_status><![CDATA[closed]]></wp_ping_status>
    <wp_post_name><![CDATA[collaboration-with-p-o-s]]></wp_post_name>
    <wp_status><![CDATA[publish]]></wp_status>
    <wp_post_parent>0</wp_post_parent>
    <wp_menu_order>0</wp_menu_order>
    <wp_post_type><![CDATA[post]]></wp_post_type>
    <wp_post_password><![CDATA[]]></wp_post_password>
    <wp_is_sticky>0</wp_is_sticky>
    <category domain="category" nicename="internal-memos"><![CDATA[Internal Memos]]></category>
    <wp_postmeta>
      <wp_meta_key><![CDATA[_edit_last]]></wp_meta_key>
      <wp_meta_value><![CDATA[1]]></wp_meta_value>
    </wp_postmeta>
    <wp_postmeta>
      <wp_meta_key><![CDATA[_thumbnail_id]]></wp_meta_key>
      <wp_meta_value><![CDATA[3530]]></wp_meta_value>
    </wp_postmeta>
    <wp_postmeta>
      <wp_meta_key><![CDATA[jumbo]]></wp_meta_key>
      <wp_meta_value><![CDATA[http://www.crimethinc.com/blog/wp-content/uploads/2012/10/POScollageb.jpg]]></wp_meta_value>
    </wp_postmeta>
    <wp_postmeta>
      <wp_meta_key><![CDATA[_cws_is_markdown]]></wp_meta_key>
      <wp_meta_value><![CDATA[1]]></wp_meta_value>
    </wp_postmeta>
    <wp_postmeta>
      <wp_meta_key><![CDATA[shorturl]]></wp_meta_key>
      <wp_meta_value><![CDATA[http://cwc.im/pos]]></wp_meta_value>
    </wp_postmeta>
    <wp_postmeta>
      <wp_meta_key><![CDATA[_sd_is_markdown]]></wp_meta_key>
      <wp_meta_value><![CDATA[1]]></wp_meta_value>
    </wp_postmeta>
    <wp_comment>
      <wp_comment_id>1712</wp_comment_id>
      <wp_comment_author><![CDATA[e. poe]]></wp_comment_author>
      <wp_comment_author_email><![CDATA[sean.distro@gmail.com]]></wp_comment_author_email>
      <wp_comment_author_url/>
      <wp_comment_author_IP><![CDATA[216.67.121.234]]></wp_comment_author_IP>
      <wp_comment_date><![CDATA[2012-10-23 04:11:30]]></wp_comment_date>
      <wp_comment_date_gmt><![CDATA[2012-10-23 04:11:30]]></wp_comment_date_gmt>
      <wp_comment_content><![CDATA[AWESOME]]></wp_comment_content>
      <wp_comment_approved><![CDATA[1]]></wp_comment_approved>
      <wp_comment_type><![CDATA[]]></wp_comment_type>
      <wp_comment_parent>0</wp_comment_parent>
      <wp_comment_user_id>23</wp_comment_user_id>
      <wp_commentmeta>
        <wp_meta_key><![CDATA[akismet_result]]></wp_meta_key>
        <wp_meta_value><![CDATA[false]]></wp_meta_value>
      </wp_commentmeta>
      <wp_commentmeta>
        <wp_meta_key><![CDATA[akismet_history]]></wp_meta_key>
        <wp_meta_value><![CDATA[a:4:{s:4:"time";s:13:"1350965490.45";s:7:"message";s:28:"Akismet cleared this comment";s:5:"event";s:9:"check-ham";s:4:"user";s:6:"e. poe";}]]></wp_meta_value>
      </wp_commentmeta>
    </wp_comment>
  </item>