<item>
		<title>Rolling Thunder #9 Full PDF Now Available</title>
		<link>http://www.crimethinc.com/blog/2016/01/19/rolling-thunder-9-full-pdf-now-available/</link>
		<pubDate>Tue, 19 Jan 2016 18:51:47 +0000</pubDate>
		<dc_creator><![CDATA[pfm]]></dc_creator>
		<guid isPermaLink="false">http://www.crimethinc.com/blog/?p=6150</guid>
		<description/>
		<content_encoded><![CDATA[<p>We've just mailed out the last print copy of <a href="https://twitter.com/crimethinc/status/682632960617484288"><em>Rolling Thunder</em> #9</a>, and as such, we're very happy to make the <a href="http://www.crimethinc.com/rt/archives.html#9"><strong>full issue available for download as a beautiful, high-resolution PDF</strong></a>. With issue #9 we were really hitting our stride, and its contents still hold up quite well:</p>

<blockquote>How important is legitimacy—in our own eyes, in the eyes of potential allies, in the eyes of the public? How can anarchists cultivate it? What pitfalls does it hold? Rolling Thunder #9 explores these questions while reporting on the past six months of upheavals around the US. Following up on our coverage of the 2008 convention protests, this issue assesses anarchist action at the 2009 G20 summit, mapping conflict throughout the city and analyzing the strategies of the police and protesters. The accompanying Pittsburgh scene report examines the decade of local organizing that prepared the ground for this and other confrontations. Elsewhere herein, we scrutinize protest and resistance on campus—from the recent occupation movement to efforts to shut down fascist student organizations—and overseas in the Smash EDO campaign. All this, plus obscure Russian history, a reappraisal of the concept of “free speech,” and the usual stunning prose. No advertisements; 16 full-color pages.</blockquote>

<p>We’ve taken this opportunity to add <a href="http://www.crimethinc.com/rt/index.html#12"><em>Rolling Thunder</em> #12</a> (the most current issues) to the <a href="http://www.crimethinc.com/rt/index.html#bundle"><em>Rolling Thunder</em> Bundle</a>, now containing issues #8, #10, #11, and #12 for just $10. And, don’t forget, you can <a href="http://www.crimethinc.com/rt/subscribe.html">subscribe to Rolling Thunder</a> to get future issues hot off the press, while also supporting the project and ensuring the journal’s continued existence. Our current plan is to release issue #13 this spring.</p>
]]></content_encoded>
		<excerpt:encoded><![CDATA[]]></excerpt:encoded>
		<wp_post_id>6150</wp_post_id>
		<wp_post_date><![CDATA[2016-01-19 10:51:47]]></wp_post_date>
		<wp_post_date_gmt><![CDATA[2016-01-19 18:51:47]]></wp_post_date_gmt>
		<wp_comment_status><![CDATA[open]]></wp_comment_status>
		<wp_ping_status><![CDATA[closed]]></wp_ping_status>
		<wp_post_name><![CDATA[rolling-thunder-9-full-pdf-now-available]]></wp_post_name>
		<wp_status><![CDATA[publish]]></wp_status>
		<wp_post_parent>0</wp_post_parent>
		<wp_menu_order>0</wp_menu_order>
		<wp_post_type><![CDATA[post]]></wp_post_type>
		<wp_post_password><![CDATA[]]></wp_post_password>
		<wp_is_sticky>0</wp_is_sticky>
		<category domain="category" nicename="read-all-about-it"><![CDATA[Read All About It]]></category>
		<wp_postmeta>
			<wp_meta_key><![CDATA[_edit_last]]></wp_meta_key>
			<wp_meta_value><![CDATA[1]]></wp_meta_value>
		</wp_postmeta>
		<wp_postmeta>
			<wp_meta_key><![CDATA[_sd_is_markdown]]></wp_meta_key>
			<wp_meta_value><![CDATA[1]]></wp_meta_value>
		</wp_postmeta>
		<wp_postmeta>
			<wp_meta_key><![CDATA[_thumbnail_id]]></wp_meta_key>
			<wp_meta_value><![CDATA[6152]]></wp_meta_value>
		</wp_postmeta>
		<wp_postmeta>
			<wp_meta_key><![CDATA[jumbo]]></wp_meta_key>
			<wp_meta_value><![CDATA[http://www.crimethinc.com/blog/wp-content/uploads/2016/01/rt9-collage-largeb.jpg]]></wp_meta_value>
		</wp_postmeta>
		<wp_postmeta>
			<wp_meta_key><![CDATA[shorturl]]></wp_meta_key>
			<wp_meta_value><![CDATA[http://cwc.im/rt9pdfannounce]]></wp_meta_value>
		</wp_postmeta>
	</item>